fossa/__init__.py
fossa/app.py
fossa/main.py
fossa/model_experiment.py
fossa/utils.py
fossa/control/__init__.py
fossa/control/broker.py
fossa/control/governor.py
fossa/control/message.py
fossa/control/process.py
fossa/control/rabbit_mq/__init__.py
fossa/control/rabbit_mq/message_exchange.py
fossa/control/rabbit_mq/pika_client.py
fossa/control/rabbit_mq/process.py
fossa/control/rabbit_mq/process_pool.py
fossa/settings/global_config.py
fossa/templates/base.html
fossa/templates/macro.html
fossa/templates/task_details.html
fossa/templates/web_root.html
fossa/tools/__init__.py
fossa/tools/logging.py
fossa/tools/logging_cloudwatch.py
fossa/views/__init__.py
fossa/views/api.py
fossa/views/controller.py
fossa/views/web.py
ayeaye_fossa-0.0.37.dist-info/LICENSE
ayeaye_fossa-0.0.37.dist-info/METADATA
ayeaye_fossa-0.0.37.dist-info/WHEEL
ayeaye_fossa-0.0.37.dist-info/top_level.txt
ayeaye_fossa-0.0.37.dist-info/RECORD
