Metadata-Version: 2.1
Name: ayeaye-fossa
Version: 0.0.37
Summary: Execution engine for Aye-Aye ETL models
Home-page: https://github.com/Aye-Aye-Dev/Fossa
Author: Si Parker
Author-email: ayeaye@plogic.co.uk
Project-URL: Bug Tracker, https://github.com/Aye-Aye-Dev/Fossa/issues
Classifier: Development Status :: 4 - Beta
Classifier: Programming Language :: Python :: 3
Classifier: License :: OSI Approved :: Apache Software License
Classifier: Operating System :: OS Independent
Requires-Python: >=3.8
License-File: LICENSE
Requires-Dist: flask
Requires-Dist: gunicorn
Requires-Dist: ayeaye >=0.0.56
Requires-Dist: pika
Requires-Dist: boto3
